pyoptimize/__init__.py
pyoptimize/main.py
pyoptimize/nn.py
pyoptimize-0.0.3.dist-info/METADATA
pyoptimize-0.0.3.dist-info/WHEEL
pyoptimize-0.0.3.dist-info/top_level.txt
pyoptimize-0.0.3.dist-info/RECORD
